azure/mgmt/datafactory/__init__.py
azure/mgmt/datafactory/_configuration.py
azure/mgmt/datafactory/_data_factory_management_client.py
azure/mgmt/datafactory/_patch.py
azure/mgmt/datafactory/_serialization.py
azure/mgmt/datafactory/_version.py
azure/mgmt/datafactory/py.typed
azure/mgmt/datafactory/aio/__init__.py
azure/mgmt/datafactory/aio/_configuration.py
azure/mgmt/datafactory/aio/_data_factory_management_client.py
azure/mgmt/datafactory/aio/_patch.py
azure/mgmt/datafactory/aio/operations/__init__.py
azure/mgmt/datafactory/aio/operations/_activity_runs_operations.py
azure/mgmt/datafactory/aio/operations/_change_data_capture_operations.py
azure/mgmt/datafactory/aio/operations/_credential_operations_operations.py
azure/mgmt/datafactory/aio/operations/_data_flow_debug_session_operations.py
azure/mgmt/datafactory/aio/operations/_data_flows_operations.py
azure/mgmt/datafactory/aio/operations/_datasets_operations.py
azure/mgmt/datafactory/aio/operations/_exposure_control_operations.py
azure/mgmt/datafactory/aio/operations/_factories_operations.py
azure/mgmt/datafactory/aio/operations/_global_parameters_operations.py
azure/mgmt/datafactory/aio/operations/_integration_runtime_nodes_operations.py
azure/mgmt/datafactory/aio/operations/_integration_runtime_object_metadata_operations.py
azure/mgmt/datafactory/aio/operations/_integration_runtimes_operations.py
azure/mgmt/datafactory/aio/operations/_linked_services_operations.py
azure/mgmt/datafactory/aio/operations/_managed_private_endpoints_operations.py
azure/mgmt/datafactory/aio/operations/_managed_virtual_networks_operations.py
azure/mgmt/datafactory/aio/operations/_operations.py
azure/mgmt/datafactory/aio/operations/_patch.py
azure/mgmt/datafactory/aio/operations/_pipeline_runs_operations.py
azure/mgmt/datafactory/aio/operations/_pipelines_operations.py
azure/mgmt/datafactory/aio/operations/_private_end_point_connections_operations.py
azure/mgmt/datafactory/aio/operations/_private_endpoint_connection_operations.py
azure_mgmt_datafactory-9.1.0.dist-info/LICENSE
azure_mgmt_datafactory-9.1.0.dist-info/METADATA
azure_mgmt_datafactory-9.1.0.dist-info/WHEEL
azure_mgmt_datafactory-9.1.0.dist-info/top_level.txt
azure_mgmt_datafactory-9.1.0.dist-info/RECORD
